datadome_encryption/__init__.py
datadome_encryption/decryption.py
datadome_encryption/encryption.py
datadome_encryption-1.1.1.dist-info/licenses/LICENSE
datadome_encryption-1.1.1.dist-info/METADATA
datadome_encryption-1.1.1.dist-info/WHEEL
datadome_encryption-1.1.1.dist-info/top_level.txt
datadome_encryption-1.1.1.dist-info/RECORD
