Metadata-Version: 2.4
Name: datadome-encryption
Version: 1.1.1
Summary: Python implementation of DataDome's client-side encryption and decryption.
Author-email: GlizzyKingDreko <glizzykingdreko@protonmail.com>
License: MIT License
Project-URL: Homepage, https://github.com/GlizzyKingDreko/datadome-encryption-python
Project-URL: Documentation, https://github.com/GlizzyKingDreko/datadome-encryption-python#readme
Project-URL: Medium, https://medium.com/@glizzykingdreko/breaking-down-datadome-captcha-waf-d7b68cef3e21
Project-URL: NodeJS, https://github.com/GlizzyKingDreko/datadome-encryption
Requires-Python: >=3.7
License-File: LICENSE
Dynamic: license-file
